README
setup.py
bambu_gensite/__init__.py
bambu_gensite/templatetags.py
bambu_gensite.egg-info/PKG-INFO
bambu_gensite.egg-info/SOURCES.txt
bambu_gensite.egg-info/dependency_links.txt
bambu_gensite.egg-info/requires.txt
bambu_gensite.egg-info/top_level.txt
bambu_gensite/generators/__init__.py
bambu_gensite/generators/auth.py
bambu_gensite/management/__init__.py
bambu_gensite/management/commands/__init__.py
bambu_gensite/management/commands/gensite.py