Metadata-Version: 1.1
Name: bambu-gensite
Version: 1.1
Summary: Fill a website with data generated from a YAML file
Home-page: https://github.com/iamsteadman/bambu-gensite
Author: Steadman
Author-email: mark@steadman.io
License: UNKNOWN
Platform: UNKNOWN
Classifier: Development Status :: 4 - Beta
Classifier: Environment :: Web Environment
Classifier: Framework :: Django
